chiklisp_loader.py
chiklisp_loader-0.1.2.dist-info/LICENSE
chiklisp_loader-0.1.2.dist-info/METADATA
chiklisp_loader-0.1.2.dist-info/WHEEL
chiklisp_loader-0.1.2.dist-info/top_level.txt
chiklisp_loader-0.1.2.dist-info/RECORD
